mglob.py
setup.py
mglob.egg-info/PKG-INFO
mglob.egg-info/SOURCES.txt
mglob.egg-info/dependency_links.txt
mglob.egg-info/entry_points.txt
mglob.egg-info/top_level.txt
