Metadata-Version: 1.0
Name: mglob
Version: 0.4
Summary: Enhanced file name globbing module
Home-page: http://vvtools.googlecode.com/svn/trunk/mglob#egg=mglob-dev
Author: Ville Vainio
Author-email: vivainio@gmail.com
License: MIT
Keywords: glob wildcard
Platform: UNKNOWN
